odoo8_addon_sale_sourced_by_line_sale_transport_multi_address-8.0.1.0.0.99.dev11-py3.8-nspkg.pth
odoo_addons/sale_sourced_by_line_sale_transport_multi_address/README.rst
odoo_addons/sale_sourced_by_line_sale_transport_multi_address/__init__.py
odoo_addons/sale_sourced_by_line_sale_transport_multi_address/__openerp__.py
odoo_addons/sale_sourced_by_line_sale_transport_multi_address/i18n/ca.po
odoo_addons/sale_sourced_by_line_sale_transport_multi_address/i18n/de.po
odoo_addons/sale_sourced_by_line_sale_transport_multi_address/i18n/es.po
odoo_addons/sale_sourced_by_line_sale_transport_multi_address/i18n/fr.po
odoo_addons/sale_sourced_by_line_sale_transport_multi_address/i18n/it.po
odoo_addons/sale_sourced_by_line_sale_transport_multi_address/i18n/nl_NL.po
odoo_addons/sale_sourced_by_line_sale_transport_multi_address/i18n/pt_BR.po
odoo_addons/sale_sourced_by_line_sale_transport_multi_address/i18n/ro.po
odoo_addons/sale_sourced_by_line_sale_transport_multi_address/i18n/sale_sourced_by_line_sale_transport_multi_address.pot
odoo_addons/sale_sourced_by_line_sale_transport_multi_address/i18n/sk.po
odoo_addons/sale_sourced_by_line_sale_transport_multi_address/i18n/sl.po
odoo_addons/sale_sourced_by_line_sale_transport_multi_address/i18n/tr.po
odoo_addons/sale_sourced_by_line_sale_transport_multi_address/i18n/tr_TR.po
odoo_addons/sale_sourced_by_line_sale_transport_multi_address/model/__init__.py
odoo_addons/sale_sourced_by_line_sale_transport_multi_address/model/sale_order_line.py
odoo_addons/sale_sourced_by_line_sale_transport_multi_address/static/description/icon.png
odoo8_addon_sale_sourced_by_line_sale_transport_multi_address-8.0.1.0.0.99.dev11.dist-info/METADATA
odoo8_addon_sale_sourced_by_line_sale_transport_multi_address-8.0.1.0.0.99.dev11.dist-info/WHEEL
odoo8_addon_sale_sourced_by_line_sale_transport_multi_address-8.0.1.0.0.99.dev11.dist-info/namespace_packages.txt
odoo8_addon_sale_sourced_by_line_sale_transport_multi_address-8.0.1.0.0.99.dev11.dist-info/top_level.txt
odoo8_addon_sale_sourced_by_line_sale_transport_multi_address-8.0.1.0.0.99.dev11.dist-info/RECORD
